orderable_inlines
