Metadata-Version: 1.0
Name: django-orderable-inlines
Version: 0.0.6
Summary: Drag-to-reorder inline model admins for Django
Home-page: https://github.com/elijahr/django-orderable-inlines
Author: Elijah Rutschman
Author-email: elijahr+django-orderable-inlines@gmail.com
License: Copyright (c) 2012, Elijah Rutschman
